Metadata-Version: 2.1
Name: faithquant
Version: 0.0.1
Summary: FaithQuant BackTest Framework
Keywords: faithquant,fqdatac,datavita,fatbulls,fatbull,fqprism
Author: Jeffrey
Author-email: wangjiangfeng@hcyjs.com
Requires-Python: >=3.10,<4.0
Classifier: Programming Language :: Python :: 3
Classifier: Programming Language :: Python :: 3.10
Classifier: Programming Language :: Python :: 3.11
Requires-Dist: PyYAML (>=6.0.1,<7.0.0)
Requires-Dist: click (>=8.1.6,<9.0.0)
Requires-Dist: cython (>=3.0.0,<4.0.0)
Requires-Dist: dill (>=0.2.5,<0.3.0)
Requires-Dist: duckdb (>=0.8.1,<0.9.0)
Requires-Dist: future (>=0.18.2,<0.19.0)
Requires-Dist: h5py (>=3.9,<4.0)
Requires-Dist: jsonpickle (>=0.9.4,<0.10.0)
Requires-Dist: logbook (>=1.0.0,<2.0.0)
Requires-Dist: loguru (>=0.7.0,<0.8.0)
Requires-Dist: numpy (>=1.23.5,<2.0.0)
Requires-Dist: pandas (>=2.0,<3.0)
Requires-Dist: pycrypto (>=2.6.1,<3.0.0)
Requires-Dist: pycryptodomex (>=3.9.9,<4.0.0)
Requires-Dist: python-dateutil (>=2.5.3,<3.0.0)
Requires-Dist: requests (>=2.31.0,<3.0.0)
Requires-Dist: simplejson (>=3.10.0,<4.0.0)
Requires-Dist: six (>=1.10.0,<2.0.0)
Requires-Dist: tabulate (>=0.9.0,<0.10.0)
